{
  "emergencias": {
    "remote_modified_time": "2026-07-14T18:50:47.141Z",
    "local_updated_at": "2026-07-14T20:43:49.577467",
    "status": "atualizado",
    "record_count": 18,
    "last_error": null
  },
  "pagamentos": {
    "remote_modified_time": "2026-07-09T14:14:47.065Z",
    "local_updated_at": "2026-07-14T20:43:54.436743",
    "status": "atualizado",
    "record_count": 29,
    "last_error": null
  },
  "devolucoes": {
    "remote_modified_time": "2026-07-13T22:43:51.313Z",
    "local_updated_at": "2026-07-14T20:45:18.009373",
    "status": "atualizado",
    "record_count": 330,
    "last_error": null
  },
  "reparaveis": {
    "remote_modified_time": "2026-07-14T14:10:36.424Z",
    "local_updated_at": "2026-07-14T20:45:13.152958",
    "status": "atualizado",
    "record_count": 446,
    "last_error": null
  }
}