{
  "disponibilidade_diaria": {
    "status": "sem_novidade",
    "last_error": null,
    "remote_modified_time": "2026-07-14T11:43:12.177Z",
    "local_updated_at": "2026-07-14T16:03:25.083758",
    "record_count": 9
  },
  "rac": {
    "remote_modified_time": "2026-07-14T13:50:24.997Z",
    "local_updated_at": "2026-07-14T16:03:59.860208",
    "status": "atualizado",
    "record_count": 30,
    "last_error": null
  },
  "vencimentos_tmot": {
    "remote_modified_time": "2026-07-09T17:03:34.124Z",
    "local_updated_at": "2026-07-14T06:39:09.798824",
    "status": "atualizado",
    "record_count": 193,
    "last_error": null
  }
}